thoth/report_processing/__init__.py
thoth/report_processing/enums.py
thoth/report_processing/exceptions.py
thoth/report_processing/utils.py
thoth/report_processing/components/__init__.py
thoth/report_processing/components/adviser.py
thoth/report_processing/components/inspection.py
thoth/report_processing/components/security.py
thoth/report_processing/components/solver.py
thoth_report_processing-0.8.1.dist-info/LICENSE
thoth_report_processing-0.8.1.dist-info/METADATA
thoth_report_processing-0.8.1.dist-info/WHEEL
thoth_report_processing-0.8.1.dist-info/top_level.txt
thoth_report_processing-0.8.1.dist-info/RECORD
