Metadata-Version: 2.1
Name: thoth-report-processing
Version: 0.8.1
Summary: Code for processing report from Thoth components.
Home-page: https://github.com/thoth-station/report-processing
Download-URL: https://pypi.org/project/thoth-report-processing
Author: Francesco Murdaca
Author-email: fmurdaca@redhat.com
License: GPLv3+
Platform: UNKNOWN
License-File: LICENSE
Requires-Dist: thoth-storages
Requires-Dist: pandas
Requires-Dist: scikit-learn
Requires-Dist: numpy
Requires-Dist: tabulate
Requires-Dist: deepdiff
Requires-Dist: thoth-common
